gtirb_layout/__init__.py
gtirb_layout/__main__.py
gtirb_layout/integral_symbols.py
gtirb_layout/layout.py
gtirb_layout-1.0.0.dist-info/LICENSE.txt
gtirb_layout-1.0.0.dist-info/METADATA
gtirb_layout-1.0.0.dist-info/WHEEL
gtirb_layout-1.0.0.dist-info/top_level.txt
gtirb_layout-1.0.0.dist-info/RECORD
